{"stat.chestOpened":4,"stat.useItem.minecraft.bow":16,"stat.walkOneCm":20392,"stat.craftItem.minecraft.sign":2,"stat.leaveGame":1,"stat.pickup.minecraft.spectral_arrow":1,"stat.craftItem.minecraft.quartz_block":66,"stat.talkedToVillager":2,"stat.drop.minecraft.shield":1,"stat.jump":418,"stat.swimOneCm":417,"stat.climbOneCm":5068,"stat.fallOneCm":538,"stat.drop.minecraft.stone":1,"stat.drop.minecraft.iron_chestplate":1,"stat.drop.minecraft.feather":2,"stat.useItem.minecraft.golden_axe":1,"stat.drop.minecraft.diamond_sword":1,"stat.crouchOneCm":399,"stat.enderchestOpened":6,"stat.craftItem.minecraft.redstone":2,"stat.craftItem.minecraft.banner":3,"stat.sprintOneCm":74821,"achievement.exploreAllBiomes":{"value":0,"progress":["The Void"]},"stat.pickup.minecraft.chorus_fruit":4,"stat.craftItem.minecraft.hopper":1,"stat.pickup.minecraft.banner":16,"stat.drop.minecraft.structure_block":1,"stat.craftItem.minecraft.furnace":3,"stat.pickup.minecraft.comparator":1,"achievement.openInventory":60,"stat.pickup.minecraft.repeater":8,"stat.craftItem.minecraft.stone":35,"stat.useItem.minecraft.snowball":20,"stat.damageTaken":650,"stat.craftItem.minecraft.wooden_button":3,"stat.dispenserInspected":2,"stat.craftItem.minecraft.comparator":2,"stat.aviateOneCm":327987,"stat.craftItem.minecraft.fence":1,"stat.craftItem.minecraft.glowstone":8,"stat.flyOneCm":685570,"stat.drop.minecraft.iron_helmet":1,"stat.deaths":2,"stat.drop":8,"stat.playOneMinute":56812,"stat.sneakTime":1420,"stat.damageDealt":17,"stat.pickup.minecraft.redstone":7,"stat.craftItem.minecraft.dispenser":1,"stat.timeSinceDeath":134,"stat.hopperInspected":2,"stat.craftItem.minecraft.repeater":6,"stat.diveOneCm":219,"stat.craftItem.minecraft.sandstone":28}